setup.py
ram_dsnd_probability/Binomialdistribution.py
ram_dsnd_probability/Gaussiandistribution.py
ram_dsnd_probability/Generaldistribution.py
ram_dsnd_probability/__init__.py
ram_dsnd_probability.egg-info/PKG-INFO
ram_dsnd_probability.egg-info/SOURCES.txt
ram_dsnd_probability.egg-info/dependency_links.txt
ram_dsnd_probability.egg-info/not-zip-safe
ram_dsnd_probability.egg-info/top_level.txt