Metadata-Version: 2.1
Name: ram_dsnd_probability
Version: 1.2
Summary: Gaussian and Binomial distributions
Author: Ram Parajuli
Author-email: ramprasad.1991.rp@gmail.com
